predictmix/__init__.py
predictmix/cli.py
predictmix/config.py
predictmix/data.py
predictmix/feature_selection.py
predictmix/models.py
predictmix/pipeline.py
predictmix/plots.py
predictmix/prs.py
predictmix-0.1.1.dist-info/LICENSE
predictmix-0.1.1.dist-info/METADATA
predictmix-0.1.1.dist-info/WHEEL
predictmix-0.1.1.dist-info/entry_points.txt
predictmix-0.1.1.dist-info/top_level.txt
predictmix-0.1.1.dist-info/RECORD
