Metadata-Version: 2.1
Name: predictmix
Version: 0.1.1
Summary: PredictMix: integrated polygenic + clinical disease risk prediction pipeline
Author-email: Etienne Ntumba Kabongo <etienne.kabongo@mcgill.ca>, "Emile R. Chimusa" <emile.chimusa@northumbria.ac.uk>
License: MIT
Classifier: Development Status :: 3 - Alpha
Classifier: Intended Audience :: Science/Research
Classifier: Intended Audience :: Healthcare Industry
Classifier: License :: OSI Approved :: MIT License
Classifier: Programming Language :: Python
Classifier: Programming Language :: Python :: 3
Classifier: Programming Language :: Python :: 3.8
Classifier: Programming Language :: Python :: 3.9
Classifier: Programming Language :: Python :: 3.10
Classifier: Programming Language :: Python :: 3.11
Classifier: Topic :: Scientific/Engineering
Classifier: Topic :: Scientific/Engineering :: Bio-Informatics
Classifier: Topic :: Scientific/Engineering :: Medical Science Apps.
Classifier: Topic :: Software Development :: Libraries :: Python Modules
Requires-Python: >=3.8
License-File: LICENSE
Requires-Dist: numpy
Requires-Dist: pandas
Requires-Dist: scikit-learn
Requires-Dist: scipy
Requires-Dist: joblib
Requires-Dist: pyyaml
Requires-Dist: lime
Requires-Dist: typer >=0.7.0
Requires-Dist: matplotlib
Requires-Dist: typing-extensions
